LICENSE
README.md
setup.py
scripts/t2t
t2t/__init__.py
t2t/cli.py
t2t/consensus.py
t2t/consistency.py
t2t/nlevel.py
t2t/remap.py
t2t/transfer.py
t2t/util.py
t2t/validate.py
tax2tree.egg-info/PKG-INFO
tax2tree.egg-info/SOURCES.txt
tax2tree.egg-info/dependency_links.txt
tax2tree.egg-info/requires.txt
tax2tree.egg-info/top_level.txt